screenshots_pagepixels/__init__.py
screenshots_pagepixels/client.py
screenshots_pagepixels-1.0.4.dist-info/LICENSE.txt
screenshots_pagepixels-1.0.4.dist-info/METADATA
screenshots_pagepixels-1.0.4.dist-info/WHEEL
screenshots_pagepixels-1.0.4.dist-info/top_level.txt
screenshots_pagepixels-1.0.4.dist-info/RECORD
