Metadata-Version: 2.1
Name: screenshots-pagepixels
Version: 1.0.4
Summary: Take immediate screenshots, create scheduled screenshots, take multi-step screenshots (click links, complete forms, login to websites), and get change notifications using the PagePixels Screenshot API python wrapper.
Home-page: https://pagepixels.com
Author: PagePixels LLC
Author-email: support@pagepixels.com
License: UNKNOWN
Platform: UNKNOWN
Classifier: Development Status :: 4 - Beta
Classifier: Intended Audience :: Developers
Classifier: License :: OSI Approved :: MIT License
Classifier: Operating System :: OS Independent
Classifier: Programming Language :: Python
Classifier: Programming Language :: Python :: 3
Classifier: Programming Language :: Python :: 3.6
Classifier: Programming Language :: Python :: 3.7
Classifier: Programming Language :: Python :: 3.8
Classifier: Programming Language :: Python :: 3.9
License-File: LICENSE.txt
Requires-Dist: requests
